simpute_py/__init__.py
simpute_py/bol_imputer.py
simpute_py/cat_imputer.py
simpute_py/date_imputer.py
simpute_py/num_imputer.py
simpute_py-0.1.1.dist-info/METADATA
simpute_py-0.1.1.dist-info/WHEEL
simpute_py-0.1.1.dist-info/LICENSE
simpute_py-0.1.1.dist-info/RECORD
