Metadata-Version: 2.1
Name: simpute-py
Version: 0.1.1
Summary: A python package for simple data imputation
License: MIT
Author: Ken Wang
Requires-Python: >=3.10,<4.0
Classifier: License :: OSI Approved :: MIT License
Classifier: Programming Language :: Python :: 3
Classifier: Programming Language :: Python :: 3.10
Classifier: Programming Language :: Python :: 3.11
Requires-Dist: pandas (>=1.5,<2.0)
Requires-Dist: scikit-learn (>=1.1,<2.0)
